parkoff/base.py
parkoff/scheduler.py
parkoff-0.1.0.dist-info/METADATA
parkoff-0.1.0.dist-info/WHEEL
parkoff-0.1.0.dist-info/RECORD
