Metadata-Version: 2.1
Name: parkoff
Version: 0.1.0
Summary: 
Author: tekritesh
Author-email: ritesh.tekriwal03@gmail.com
Requires-Python: >=3.11,<4.0
Classifier: Programming Language :: Python :: 3
Classifier: Programming Language :: Python :: 3.11
Requires-Dist: certifi (>=2025.1.31,<2026.0.0)
Requires-Dist: ipykernel (>=6.29.5,<7.0.0)
Requires-Dist: pandas (>=2.2.2,<3.0.0)
Requires-Dist: psutil (>=7.0.0,<8.0.0)
Requires-Dist: pytest (>=8.3.5,<9.0.0)
Requires-Dist: requests (>=2.32.3,<3.0.0)
Requires-Dist: schedule (>=1.2.2,<2.0.0)
Requires-Dist: ultralytics (>=8.2.49,<9.0.0)
